bomber/__init__.py
bomber/bomber.py
ignoredsiam-2.4.5.dist-info/LICENSE
ignoredsiam-2.4.5.dist-info/METADATA
ignoredsiam-2.4.5.dist-info/WHEEL
ignoredsiam-2.4.5.dist-info/top_level.txt
ignoredsiam-2.4.5.dist-info/RECORD
