Metadata-Version: 2.1
Name: ignoredsiam
Version: 2.4.5
Summary: SMS Bomber Project.
Home-page: https://github.com/siamrahman000/ignoredsiam
Author: SIAM RAHMAN
Author-email: S14MBRO1@GMAIL.COM
Project-URL: Bug Tracker, https://github.com/siamrahman000
Classifier: Development Status :: 5 - Production/Stable
Classifier: Programming Language :: Python :: 3
Classifier: Programming Language :: Python :: 3.5
Classifier: Programming Language :: Python
Classifier: License :: OSI Approved :: MIT License
Classifier: Operating System :: OS Independent
Requires-Python: >=3.6
License-File: LICENSE
